setup.py
cctrl/__init__.py
cctrl/addonoptionhelpers.py
cctrl/app.py
cctrl/app_commands.py
cctrl/auth.py
cctrl/cacerts.txt
cctrl/cctrlapp
cctrl/cctrluser
cctrl/cnhapp
cctrl/cnhuser
cctrl/common.py
cctrl/dcapp
cctrl/dcuser
cctrl/error.py
cctrl/exoapp
cctrl/exouser
cctrl/keyhelpers.py
cctrl/oshelpers.py
cctrl/output.py
cctrl/settings.py
cctrl/user.py
cctrl/user_commands.py
cctrl/version.py
cnh.egg-info/PKG-INFO
cnh.egg-info/SOURCES.txt
cnh.egg-info/dependency_links.txt
cnh.egg-info/requires.txt
cnh.egg-info/top_level.txt
tests/__init__.py
tests/app_test.py
tests/config_test.py
tests/keyhelpers_test.py
tests/settings_test.py
tests/user_test.py